.gitignore
.gitmodules
Makefile
README.md
local.xsd
musicbrainz_mmd.xsd
pyproject.toml
requirements-test.txt
requirements.txt
update.sh
.github/workflows/pythonpackage.yml
bin/.gitignore
mb_rngpy.egg-info/PKG-INFO
mb_rngpy.egg-info/SOURCES.txt
mb_rngpy.egg-info/dependency_links.txt
mb_rngpy.egg-info/requires.txt
mb_rngpy.egg-info/top_level.txt
mbrng/__init__.py
mbrng/mb_mmd_subs.py
mbrng/models.py
test/test_models.py