Metadata-Version: 2.4
Name: mb-rngpy
Version: 2.20250423.0
Summary: Python bindings for the MusicBrainz XML Metadata RELAX NG schema
Author-email: MetaBrainz Foundation <support@metabrainz.org>
License-Expression: MIT
Project-URL: Homepage, https://github.com/metabrainz/mb-rngpy
Project-URL: Releases, https://github.com/metabrainz/mb-rngpy/releases
Project-URL: Issues, https://tickets.metabrainz.org/projects/SEARCH/issues/
Classifier: Development Status :: 5 - Production/Stable
Classifier: Natural Language :: English
Classifier: Operating System :: OS Independent
Classifier: Programming Language :: Python :: 3
Classifier: Topic :: Software Development :: Libraries :: Python Modules
Requires-Python: >=3
Requires-Dist: lxml==5.4.0
